my_package/__init__.py
my_package/main.py
tamilselvan_13-0.0.1.dist-info/LICENSE
tamilselvan_13-0.0.1.dist-info/METADATA
tamilselvan_13-0.0.1.dist-info/WHEEL
tamilselvan_13-0.0.1.dist-info/top_level.txt
tamilselvan_13-0.0.1.dist-info/RECORD
